DadosHelpers
